CHANGELOG.txt
CODE_OF_CONDUCT.md
CONTRIBUTORS.rst
LICENSE
MANIFEST.in
README.md
SECURITY.md
SPONSORS.md
setup.cfg
setup.py
wagtail/.gitignore
wagtail/__init__.py
wagtail/apps.py
wagtail/coreutils.py
wagtail/edit_handlers.py
wagtail/fields.py
wagtail/forms.py
wagtail/hooks.py
wagtail/jinja2tags.py
wagtail/logging.py
wagtail/permissions.py
wagtail/signal_handlers.py
wagtail/signals.py
wagtail/urls.py
wagtail/views.py
wagtail/widget_adapters.py
wagtail/workflows.py
wagtail/admin/.gitignore
wagtail/admin/__init__.py
wagtail/admin/action_menu.py
wagtail/admin/admin_url_finder.py
wagtail/admin/apps.py
wagtail/admin/auth.py
wagtail/admin/blocks.py
wagtail/admin/checks.py
wagtail/admin/compare.py
wagtail/admin/datetimepicker.py
wagtail/admin/edit_handlers.py
wagtail/admin/filters.py
wagtail/admin/jinja2tags.py
wagtail/admin/locales.py
wagtail/admin/localization.py
wagtail/admin/mail.py
wagtail/admin/menu.py
wagtail/admin/messages.py
wagtail/admin/modal_workflow.py
wagtail/admin/navigation.py
wagtail/admin/search.py
wagtail/admin/signal_handlers.py
wagtail/admin/signals.py
wagtail/admin/site_summary.py
wagtail/admin/staticfiles.py
wagtail/admin/userbar.py
wagtail/admin/usersutils.py
wagtail/admin/api/__init__.py
wagtail/admin/api/filters.py
wagtail/admin/api/serializers.py
wagtail/admin/api/urls.py
wagtail/admin/api/views.py
wagtail/admin/forms/__init__.py
wagtail/admin/forms/account.py
wagtail/admin/forms/auth.py
wagtail/admin/forms/choosers.py
wagtail/admin/forms/collections.py
wagtail/admin/forms/comments.py
wagtail/admin/forms/locales.py
wagtail/admin/forms/models.py
wagtail/admin/forms/pages.py
wagtail/admin/forms/search.py
wagtail/admin/forms/sites.py
wagtail/admin/forms/tags.py
wagtail/admin/forms/users.py
wagtail/admin/forms/view_restrictions.py
wagtail/admin/forms/workflows.py
wagtail/admin/migrations/0001_create_admin_access_permissions.py
wagtail/admin/migrations/0002_admin.py
wagtail/admin/migrations/0003_admin_managed.py
wagtail_restructure.egg-info/PKG-INFO
wagtail_restructure.egg-info/SOURCES.txt
wagtail_restructure.egg-info/dependency_links.txt
wagtail_restructure.egg-info/entry_points.txt
wagtail_restructure.egg-info/not-zip-safe
wagtail_restructure.egg-info/requires.txt
wagtail_restructure.egg-info/top_level.txt