Metadata-Version: 2.1
Name: wagtail-restructure
Version: 2.16a0
Summary: A Django content management system.
Home-page: https://wagtail.io/
Author: Wagtail core team + contributors
Author-email: hello@wagtail.io
License: BSD
Platform: UNKNOWN
Classifier: Development Status :: 5 - Production/Stable
Classifier: Environment :: Web Environment
Classifier: Intended Audience :: Developers
Classifier: License :: OSI Approved :: BSD License
Classifier: Operating System :: OS Independent
Classifier: Programming Language :: Python
Classifier: Programming Language :: Python :: 3
Classifier: Programming Language :: Python :: 3.6
Classifier: Programming Language :: Python :: 3.7
Classifier: Programming Language :: Python :: 3.8
Classifier: Programming Language :: Python :: 3.9
Classifier: Programming Language :: Python :: 3.10
Classifier: Framework :: Django
Classifier: Framework :: Django :: 3.0
Classifier: Framework :: Django :: 3.1
Classifier: Framework :: Django :: 3.2
Classifier: Framework :: Wagtail
Classifier: Topic :: Internet :: WWW/HTTP :: Site Management
Requires-Python: >=3.6
Provides-Extra: testing
Provides-Extra: docs
License-File: LICENSE
